friendship/__init__.py
friendship/admin.py
friendship/apps.py
friendship/exceptions.py
friendship/models.py
friendship/signals.py
friendship/urls.py
friendship/views.py
friendship/migrations/0001_initial.py
friendship/migrations/0002_block.py
friendship/migrations/0003_block_unique_together.py
friendship/migrations/0004_auto_20200408_1844.py
friendship/migrations/__init__.py
friendship/south_migrations/0001_initial.py
friendship/south_migrations/__init__.py
friendship/templates/404.html
friendship/templates/friendship/base.html
friendship/templates/friendship/header.html
friendship/templates/friendship/user_actions.html
friendship/templates/friendship/block/add.html
friendship/templates/friendship/block/blocked_list.html
friendship/templates/friendship/block/blockers_list.html
friendship/templates/friendship/block/blocking_list.html
friendship/templates/friendship/block/remove.html
friendship/templates/friendship/follow/add.html
friendship/templates/friendship/follow/followers_list.html
friendship/templates/friendship/follow/following_list.html
friendship/templates/friendship/follow/remove.html
friendship/templates/friendship/friend/add.html
friendship/templates/friendship/friend/request.html
friendship/templates/friendship/friend/requests_list.html
friendship/templates/friendship/friend/user_list.html
friendship/templates/friendship/templatetags/blockers.html
friendship/templates/friendship/templatetags/blocking.html
friendship/templates/friendship/templatetags/followers.html
friendship/templates/friendship/templatetags/following.html
friendship/templates/friendship/templatetags/friend_count.html
friendship/templates/friendship/templatetags/friend_rejected_count.html
friendship/templates/friendship/templatetags/friend_request_count.html
friendship/templates/friendship/templatetags/friend_requests.html
friendship/templates/friendship/templatetags/friends.html
friendship/templatetags/__init__.py
friendship/templatetags/friendshiptags.py
friendship/tests/__init__.py
django_friendship-1.9.6.dist-info/LICENSE.txt
django_friendship-1.9.6.dist-info/METADATA
django_friendship-1.9.6.dist-info/WHEEL
django_friendship-1.9.6.dist-info/top_level.txt
django_friendship-1.9.6.dist-info/RECORD
